[
  {
    "date": "2022-03-31T00:00:00+09:00",
    "date_display": "2022-Q1",
    "암호화폐": 50,
    "스타트업투자": 30
  },
  {
    "date": "2022-06-30T00:00:00+09:00",
    "date_display": "2022-Q2",
    "암호화폐": 45,
    "스타트업투자": 25
  },
  {
    "date": "2022-09-30T00:00:00+09:00",
    "date_display": "2022-Q3",
    "암호화폐": 55,
    "스타트업투자": 35
  },
  {
    "date": "2022-12-31T00:00:00+09:00",
    "date_display": "2022-Q4",
    "암호화폐": -380,
    "스타트업투자": 28
  },
  {
    "date": "2023-03-31T00:00:00+09:00",
    "date_display": "2023-Q1",
    "암호화폐": 60,
    "스타트업투자": 40
  },
  {
    "date": "2023-06-30T00:00:00+09:00",
    "date_display": "2023-Q2",
    "암호화폐": 48,
    "스타트업투자": -420
  },
  {
    "date": "2023-09-30T00:00:00+09:00",
    "date_display": "2023-Q3",
    "암호화폐": 52,
    "스타트업투자": 32
  },
  {
    "date": "2023-12-31T00:00:00+09:00",
    "date_display": "2023-Q4",
    "암호화폐": 58,
    "스타트업투자": 38
  },
  {
    "date": "2024-03-31T00:00:00+09:00",
    "date_display": "2024-Q1",
    "암호화폐": 65,
    "스타트업투자": 42
  },
  {
    "date": "2024-06-30T00:00:00+09:00",
    "date_display": "2024-Q2",
    "암호화폐": 47,
    "스타트업투자": 27
  },
  {
    "date": "2024-09-30T00:00:00+09:00",
    "date_display": "2024-Q3",
    "암호화폐": 53,
    "스타트업투자": 33
  },
  {
    "date": "2024-12-31T00:00:00+09:00",
    "date_display": "2024-Q4",
    "암호화폐": 56,
    "스타트업투자": 36
  },
  {
    "date": "2025-03-31T00:00:00+09:00",
    "date_display": "2025-Q1",
    "암호화폐": 49,
    "스타트업투자": 29
  },
  {
    "date": "2025-06-30T00:00:00+09:00",
    "date_display": "2025-Q2",
    "암호화폐": 54,
    "스타트업투자": 34
  },
  {
    "date": "2025-09-30T00:00:00+09:00",
    "date_display": "2025-Q3",
    "암호화폐": 500,
    "스타트업투자": 40
  }
]
